fastapi_error_logger/__init__.py
fastapi_error_logger/api_logger.py
fastapi_error_logger/exceptions.py
fastapi_error_logger/models.py
fastapi_error_logger-0.1.2.dist-info/LICENSE
fastapi_error_logger-0.1.2.dist-info/METADATA
fastapi_error_logger-0.1.2.dist-info/WHEEL
fastapi_error_logger-0.1.2.dist-info/top_level.txt
fastapi_error_logger-0.1.2.dist-info/RECORD
