Metadata-Version: 2.1
Name: fastapi-error-logger
Version: 0.1.2
License: MIT
Project-URL: Source, https://github.com/omkardarves/fastapi-error-logger
License-File: LICENSE
Requires-Dist: fastapi
Requires-Dist: sqlalchemy
